atomheart/__init__.py
atomheart/move_factory.py
atomheart/transition.py
atomheart/board/__init__.py
atomheart/board/board_chi.py
atomheart/board/board_modification.py
atomheart/board/board_tools.py
atomheart/board/factory.py
atomheart/board/iboard.py
atomheart/board/rusty_board.py
atomheart/board/starting_position.py
atomheart/board/utils.py
atomheart/board/valanga_adapter.py
atomheart/move/__init__.py
atomheart/move/imove.py
atomheart/move/rust_move.py
atomheart/move/utils.py
atomheart/utils/color.py
atomheart/utils/logger.py
atomheart-0.1.6.dist-info/licenses/LICENSE
atomheart-0.1.6.dist-info/METADATA
atomheart-0.1.6.dist-info/WHEEL
atomheart-0.1.6.dist-info/top_level.txt
atomheart-0.1.6.dist-info/RECORD
